cookiecutter/__init__.py
cookiecutter/__main__.py
cookiecutter/cli.py
cookiecutter/config.py
cookiecutter/environment.py
cookiecutter/exceptions.py
cookiecutter/extensions.py
cookiecutter/find.py
cookiecutter/generate.py
cookiecutter/hooks.py
cookiecutter/log.py
cookiecutter/main.py
cookiecutter/prompt.py
cookiecutter/replay.py
cookiecutter/repository.py
cookiecutter/utils.py
cookiecutter/vcs.py
cookiecutter/zipfile.py
tacc_cookiecutter-1.7.0.1.dist-info/AUTHORS.md
tacc_cookiecutter-1.7.0.1.dist-info/LICENSE
tacc_cookiecutter-1.7.0.1.dist-info/METADATA
tacc_cookiecutter-1.7.0.1.dist-info/WHEEL
tacc_cookiecutter-1.7.0.1.dist-info/entry_points.txt
tacc_cookiecutter-1.7.0.1.dist-info/top_level.txt
tacc_cookiecutter-1.7.0.1.dist-info/RECORD
