Metadata-Version: 2.1
Name: tacc-cookiecutter
Version: 1.7.0.1
Summary: A command-line utility that creates projects from project templates, e.g. creating a Python package project from a Python package project template.
Home-page: https://github.com/TACC-Cloud/cookiecutter
Author: Audrey Roy (Temporarily forked by TACC)
Author-email: opensource@tacc.cloud
License: BSD
Keywords: cookiecutter,Python,projects,project templates,Jinja2,skeleton,scaffolding,project directory,setup.py,package,packaging
Platform: UNKNOWN
Classifier: Development Status :: 5 - Production/Stable
Classifier: Environment :: Console
Classifier: Intended Audience :: Developers
Classifier: Natural Language :: English
Classifier: License :: OSI Approved :: BSD License
Classifier: Programming Language :: Python
Classifier: Programming Language :: Python :: 2
Classifier: Programming Language :: Python :: 2.7
Classifier: Programming Language :: Python :: 3
Classifier: Programming Language :: Python :: 3.5
Classifier: Programming Language :: Python :: 3.6
Classifier: Programming Language :: Python :: 3.7
Classifier: Programming Language :: Python :: 3.8
Classifier: Programming Language :: Python :: Implementation :: CPython
Classifier: Programming Language :: Python :: Implementation :: PyPy
Classifier: Topic :: Software Development
Requires-Python: >=2.7, !=3.0.*, !=3.1.*, !=3.2.*, !=3.3.*, !=3.4.*
Requires-Dist: binaryornot (>=0.2.0)
Requires-Dist: jinja2 (>=2.7)
Requires-Dist: click (>=7.0)
Requires-Dist: poyo (>=0.1.0)
Requires-Dist: jinja2-time (>=0.1.0)
Requires-Dist: requests (>=2.18.0)
Requires-Dist: six (>=1.10)
Requires-Dist: whichcraft (>=0.4.0) ; python_version<"3.3"
